.gitattributes
.gitignore
CHANGELOG.md
CONTRIBUTING.md
LICENSE
MANIFEST.in
README.md
setup.cfg
setup.py
versioneer.py
nanolib.egg-info/PKG-INFO
nanolib.egg-info/SOURCES.txt
nanolib.egg-info/dependency_links.txt
nanolib.egg-info/requires.txt
nanolib.egg-info/top_level.txt
src/nanolib/__init__.py
src/nanolib/_version.py
src/nanolib/accounts.py
src/nanolib/blocks.py
src/nanolib/exceptions.py
src/nanolib/units.py
src/nanolib/util.py
src/nanolib/work.py
src/nanolib-nbase32-module/bit_array.c
src/nanolib-nbase32-module/bit_array.h
src/nanolib-nbase32-module/bit_macros.h
src/nanolib-nbase32-module/nbase32.c
src/nanolib-work-module/work.c
src/nanolib-work-module/BLAKE2/.gitignore
src/nanolib-work-module/BLAKE2/COPYING
src/nanolib-work-module/BLAKE2/README.md
src/nanolib-work-module/BLAKE2/b2sum/README.md
src/nanolib-work-module/BLAKE2/b2sum/b2sum.1
src/nanolib-work-module/BLAKE2/b2sum/b2sum.c
src/nanolib-work-module/BLAKE2/b2sum/makefile
src/nanolib-work-module/BLAKE2/bench/bench.c
src/nanolib-work-module/BLAKE2/bench/do.gplot
src/nanolib-work-module/BLAKE2/bench/makefile
src/nanolib-work-module/BLAKE2/bench/md5.c
src/nanolib-work-module/BLAKE2/csharp/Blake2Sharp.sln
src/nanolib-work-module/BLAKE2/csharp/Blake2Sharp/Blake2B.cs
src/nanolib-work-module/BLAKE2/csharp/Blake2Sharp/Blake2BConfig.cs
src/nanolib-work-module/BLAKE2/csharp/Blake2Sharp/Blake2BCore-FullyUnrolled.cs
src/nanolib-work-module/BLAKE2/csharp/Blake2Sharp/Blake2BCore-Inline.cs
src/nanolib-work-module/BLAKE2/csharp/Blake2Sharp/Blake2BCore-Simple.cs
src/nanolib-work-module/BLAKE2/csharp/Blake2Sharp/Blake2BCore.cs
src/nanolib-work-module/BLAKE2/csharp/Blake2Sharp/Blake2BHasher.cs
src/nanolib-work-module/BLAKE2/csharp/Blake2Sharp/Blake2BNodeHasher.cs
src/nanolib-work-module/BLAKE2/csharp/Blake2Sharp/Blake2BTreeConfig.cs
src/nanolib-work-module/BLAKE2/csharp/Blake2Sharp/Blake2IvBuilder.cs
src/nanolib-work-module/BLAKE2/csharp/Blake2Sharp/Blake2Sharp.csproj
src/nanolib-work-module/BLAKE2/csharp/Blake2Sharp/Hasher.cs
src/nanolib-work-module/BLAKE2/csharp/Blake2Sharp/NodeHasher.cs
src/nanolib-work-module/BLAKE2/csharp/Blake2Sharp/TreeHasher.cs
