Metadata-Version: 1.2
Name: nanolib
Version: 0.4.3
Summary: Python library for working with the NANO cryptocurrency protocol
Home-page: https://github.com/Matoking/nanolib
Author: Janne Pulkkinen
Author-email: jannepulk@gmail.com
License: CC0
Platform: UNKNOWN
Classifier: Programming Language :: Python
Classifier: Programming Language :: Python :: 3
Classifier: Programming Language :: Python :: 3.6
Classifier: Programming Language :: Python :: 3.7
Classifier: Programming Language :: Python :: 3.8
Classifier: Programming Language :: Python :: 3.9
Classifier: Programming Language :: Python :: Implementation :: CPython
Classifier: Operating System :: Microsoft :: Windows
Classifier: Operating System :: POSIX :: Linux
Classifier: Topic :: Office/Business :: Financial
Requires-Python: >=3.6.0
